{
    "plugins": [
        "-disqus",
        "-mermaid",
        "collapsible-menu",
        "fancybox",
        "youtube",
        "-search",
        "search-pro",
        "atoc"
    ],
    "pluginsConfig": {
        "-disqus": {
            "shortName": "sharefunyeh",
            "useIdentifier": true
        },
        "search-pro": {
            "cutWordLib": "nodejieba",
            "defineWord": [
                "宗岳門",
                "指領"
            ]
        },
        "atoc": {
            "addClass": true,
            "className": "atoc"
        }
    }
}